groups2/__init__.py
groups2/admin.py
groups2/forms.py
groups2/models.py
groups2/migrations/0001_initial.py
groups2/migrations/__init__.py
groups2/templates/groups2/admin/edit_users.html
groups2/templates/groups2/admin/group2_change_form.html
django_groups2-0.1.1.dist-info/LICENSE
django_groups2-0.1.1.dist-info/METADATA
django_groups2-0.1.1.dist-info/WHEEL
django_groups2-0.1.1.dist-info/top_level.txt
django_groups2-0.1.1.dist-info/RECORD
